<?xml version="1.0" encoding="utf-8" ?>
<dwsync>
<file name="SSDA_librarydatabase.php" server="//ad/webdev/SSDataArchivePHPWebSite/" local="130888255390000000" remote="130888255390000000" Dst="-1" />
<file name="index.php" server="//ad/webdev/SSDataArchivePHPWebSite/" local="130886418578616036" remote="130886418570000000" Dst="-1" />
<file name="2col_leftNav.css" server="//ad/webdev/SSDataArchivePHPWebSite/" local="128921546040000000" remote="128921546040000000" Dst="-1" />
<file name="index.html" server="//ad/webdev/SSDataArchivePHPWebSite/" local="130886421080000000" remote="130886421080000000" Dst="-1" />
<file name="da_catalog_edit.php" server="//ad/webdev/SSDataArchivePHPWebSite/" local="130903549950000000" remote="130903549950000000" Dst="2" />
<file name="da_catalog.js" server="//ad/webdev/SSDataArchivePHPWebSite/" local="129508355420000000" remote="129508355420000000" Dst="2" />
<file name="maintenance_index.html" server="//ad/webdev/SSDataArchivePHPWebSite/" local="130886431540000000" remote="130886431540000000" Dst="-1" />
<file name="SSDA_librarydatabase_edit.php" server="//ad/webdev/SSDataArchivePHPWebSite/" local="130889035830000000" remote="130889035830000000" Dst="-1" />
<file name="da_catalog_input.php" server="//ad/webdev/SSDataArchivePHPWebSite/" local="130903595615595925" remote="130903595610000000" Dst="-1" />
<file name="Security.htaccess.txt" server="//ad/webdev/SSDataArchivePHPWebSite/" local="130892332690000000" remote="130892332690000000" Dst="-1" />
<file name=".htaccess.htm" server="//ad/webdev/SSDataArchivePHPWebSite/" local="130892334120000000" remote="130892334120000000" Dst="-1" />
<file name="da_catalog_inputDatasetRecord.php" server="//ad/webdev/SSDataArchivePHPWebSite/" local="130903550756375925" remote="130903550750000000" Dst="-1" />
<file name="da_catalog_editDatasetRecord.php" server="//ad/webdev/SSDataArchivePHPWebSite/" local="130903550363635925" remote="130903550360000000" Dst="-1" />
<file name="da_catalog_processFormCheck.php" server="//ad/webdev/SSDataArchivePHPWebSite/" local="130894931294263837" remote="130894931290000000" Dst="2" />
<file name="da_catalog_updateCheck.php" server="//ad/webdev/SSDataArchivePHPWebSite/" local="130903576020000000" remote="130903576020000000" Dst="2" />
<file name="da_catalog_update.php" server="//ad/webdev/SSDataArchivePHPWebSite/" local="130904484915528830" remote="130904484910000000" Dst="2" />
<file name="da_catalog_insertCheck.php" server="//ad/webdev/SSDataArchivePHPWebSite/" local="130903597026935925" remote="130903597020000000" Dst="-1" />
<file name="da_catalog_insertPICheck.php" server="//ad/webdev/SSDataArchivePHPWebSite/" local="129498065630000000" remote="129498065630000000" Dst="2" />
</dwsync>